{
    "annotations": {
      "list": [
        {
          "builtIn": 1,
          "datasource": "-- Grafana --",
          "enable": true,
          "hide": true,
          "iconColor": "rgba(0, 211, 255, 1)",
          "name": "Annotations & Alerts",
          "type": "dashboard"
        }
      ]
    },
    "editable": true,
    "gnetId": null,
    "graphTooltip": 0,
    "id": null,
    "links": [],
    "panels": [
      {
        "aliasColors": {},
        "bars": false,
        "dashLength": 10,
        "dashes": false,
        "datasource": "Prometheus",
        "fieldConfig": {
          "defaults": {
            "unit": "percent"
          }
        },
        "fill": 1,
        "fillGradient": 0,
        "gridPos": {
          "h": 8,
          "w": 12,
          "x": 0,
          "y": 0
        },
        "hiddenSeries": false,
        "id": 2,
        "legend": {
          "avg": false,
          "current": false,
          "max": false,
          "min": false,
          "show": true,
          "total": false,
          "values": false
        },
        "lines": true,
        "linewidth": 1,
        "nullPointMode": "null",
        "options": {
          "alertThreshold": true
        },
        "percentage": false,
        "pluginVersion": "7.5.7",
        "pointradius": 2,
        "points": false,
        "renderer": "flot",
        "seriesOverrides": [],
        "spaceLength": 10,
        "stack": false,
        "steppedLine": false,
        "targets": [
          {
            "expr": "100 - (avg by (instance) (irate(node_cpu_seconds_total{mode=\"idle\"}[5m])) * 100)",
            "interval": "",
            "legendFormat": "CPU Usage",
            "refId": "A"
          }
        ],
        "thresholds": [],
        "timeRegions": [],
        "title": "CPU Usage",
        "tooltip": {
          "shared": true,
          "sort": 0,
          "value_type": "individual"
        },
        "type": "graph",
        "xaxis": {
          "mode": "time",
          "show": true,
          "values": []
        },
        "yaxes": [
          {
            "format": "percent",
            "label": "",
            "logBase": 1,
            "max": "100",
            "min": "0",
            "show": true
          },
          {
            "format": "short",
            "label": null,
            "logBase": 1,
            "max": null,
            "min": null,
            "show": true
          }
        ],
        "yaxis": {
          "align": false,
          "alignLevel": null
        }
      },
      {
        "aliasColors": {},
        "bars": false,
        "dashLength": 10,
        "dashes": false,
        "datasource": "Prometheus",
        "fieldConfig": {
          "defaults": {
            "unit": "bytes"
          }
        },
        "fill": 1,
        "fillGradient": 0,
        "gridPos": {
          "h": 8,
          "w": 12,
          "x": 12,
          "y": 0
        },
        "hiddenSeries": false,
        "id": 4,
        "legend": {
          "avg": false,
          "current": false,
          "max": false,
          "min": false,
          "show": true,
          "total": false,
          "values": false
        },
        "lines": true,
        "linewidth": 1,
        "nullPointMode": "null",
        "options": {
          "alertThreshold": true
        },
        "percentage": false,
        "pluginVersion": "7.5.7",
        "pointradius": 2,
        "points": false,
        "renderer": "flot",
        "seriesOverrides": [],
        "spaceLength": 10,
        "stack": false,
        "steppedLine": false,
        "targets": [
          {
            "expr": "node_memory_MemTotal_bytes - node_memory_MemFree_bytes - node_memory_Buffers_bytes - node_memory_Cached_bytes",
            "interval": "",
            "legendFormat": "Used Memory",
            "refId": "A"
          },
          {
            "expr": "node_memory_MemTotal_bytes",
            "interval": "",
            "legendFormat": "Total Memory",
            "refId": "B"
          }
        ],
        "thresholds": [],
        "timeRegions": [],
        "title": "Memory Usage",
        "tooltip": {
          "shared": true,
          "sort": 0,
          "value_type": "individual"
        },
        "type": "graph",
        "xaxis": {
          "mode": "time",
          "show": true,
          "values": []
        },
        "yaxes": [
          {
            "format": "bytes",
            "label": null,
            "logBase": 1,
            "max": null,
            "min": "0",
            "show": true
          },
          {
            "format": "short",
            "label": null,
            "logBase": 1,
            "max": null,
            "min": null,
            "show": true
          }
        ],
        "yaxis": {
          "align": false,
          "alignLevel": null
        }
      },
      {
        "aliasColors": {},
        "bars": false,
        "dashLength": 10,
        "dashes": false,
        "datasource": "Prometheus",
        "fieldConfig": {
          "defaults": {
            "unit": "bytes"
          }
        },
        "fill": 1,
        "fillGradient": 0,
        "gridPos": {
          "h": 8,
          "w": 24,
          "x": 0,
          "y": 8
        },
        "hiddenSeries": false,
        "id": 6,
        "legend": {
          "avg": false,
          "current": false,
          "max": false,
          "min": false,
          "show": true,
          "total": false,
          "values": false
        },
        "lines": true,
        "linewidth": 1,
        "nullPointMode": "null",
        "options": {
          "alertThreshold": true
        },
        "percentage": false,
        "pluginVersion": "7.5.7",
        "pointradius": 2,
        "points": false,
        "renderer": "flot",
        "seriesOverrides": [],
        "spaceLength": 10,
        "stack": false,
        "steppedLine": false,
        "targets": [
          {
            "expr": "node_filesystem_size_bytes{mountpoint=\"/\"} - node_filesystem_avail_bytes{mountpoint=\"/\"}",
            "interval": "",
            "legendFormat": "Used Space",
            "refId": "A"
          },
          {
            "expr": "node_filesystem_size_bytes{mountpoint=\"/\"}",
            "interval": "",
            "legendFormat": "Total Space",
            "refId": "B"
          }
        ],
        "thresholds": [],
        "timeRegions": [],
        "title": "Disk Usage",
        "tooltip": {
          "shared": true,
          "sort": 0,
          "value_type": "individual"
        },
        "type": "graph",
        "xaxis": {
          "mode": "time",
          "show": true,
          "values": []
        },
        "yaxes": [
          {
            "format": "bytes",
            "label": null,
            "logBase": 1,
            "max": null,
            "min": "0",
            "show": true
          },
          {
            "format": "short",
            "label": null,
            "logBase": 1,
            "max": null,
            "min": null,
            "show": true
          }
        ],
        "yaxis": {
          "align": false,
          "alignLevel": null
        }
      }
    ],
    "refresh": "5s",
    "schemaVersion": 27,
    "style": "dark",
    "tags": [],
    "templating": {
      "list": []
    },
    "time": {
      "from": "now-1h",
      "to": "now"
    },
    "timepicker": {},
    "timezone": "",
    "title": "System Monitoring",
    "uid": "system_monitoring",
    "version": 1
  }